ol_openedx_otel_monitoring/__init__.py
ol_openedx_otel_monitoring/apps.py
ol_openedx_otel_monitoring/client.py
ol_openedx_otel_monitoring/exceptions.py
ol_openedx_otel_monitoring/metrics.py
ol_openedx_otel_monitoring/middleware.py
ol_openedx_otel_monitoring/tracing.py
ol_openedx_otel_monitoring/urls.py
ol_openedx_otel_monitoring/views.py
ol_openedx_otel_monitoring/settings/__init__.py
ol_openedx_otel_monitoring/settings/common.py
ol_openedx_otel_monitoring/settings/production.py
ol_openedx_otel_monitoring-0.2.0.dist-info/METADATA
ol_openedx_otel_monitoring-0.2.0.dist-info/WHEEL
ol_openedx_otel_monitoring-0.2.0.dist-info/entry_points.txt
ol_openedx_otel_monitoring-0.2.0.dist-info/licenses/LICENSE.txt
ol_openedx_otel_monitoring-0.2.0.dist-info/RECORD
