Metadata-Version: 2.4
Name: ol-openedx-otel-monitoring
Version: 0.2.0
Summary: OTel Monitoring
Author: MIT Office of Digital Learning
License-Expression: BSD-3-Clause
License-File: LICENSE.txt
Requires-Python: >=3.11
Requires-Dist: django>=4.0
Requires-Dist: opentelemetry-distro
Requires-Dist: opentelemetry-exporter-otlp-proto-http
Requires-Dist: opentelemetry-exporter-richconsole
Requires-Dist: opentelemetry-instrumentation-django
